fileformats/medimage/__init__.py
fileformats/medimage/_version.py
fileformats/medimage/base.py
fileformats/medimage/dicom.py
fileformats/medimage/diffusion.py
fileformats/medimage/itk.py
fileformats/medimage/misc.py
fileformats/medimage/nifti.py
fileformats/medimage/py.typed
fileformats/medimage/surface.py
fileformats/medimage/contents/__init__.py
fileformats/medimage/contents/anatomical_entity/__init__.py
fileformats/medimage/contents/anatomical_entity/anatomical_set.py
fileformats/medimage/contents/anatomical_entity/immaterial_anatomical_entity.py
fileformats/medimage/contents/anatomical_entity/material_anatomical_entity/__init__.py
fileformats/medimage/contents/anatomical_entity/material_anatomical_entity/anatomical_structure.py
fileformats/medimage/contents/imaging/__init__.py
fileformats/medimage/contents/imaging/derivatives.py
fileformats/medimage/contents/imaging/modality.py
fileformats/medimage/contents/property/__init__.py
fileformats/medimage/contents/property/imaging_procedure/__init__.py
fileformats/medimage/contents/property/imaging_procedure/cross_sectional_procedure/__init__.py
fileformats/medimage/contents/property/imaging_procedure/cross_sectional_procedure/mr_procedure/__init__.py
fileformats/medimage/contents/property/imaging_procedure/cross_sectional_procedure/mr_procedure/tissue_contrast.py
fileformats/medimage/raw/__init__.py
fileformats/medimage/raw/mri/__init__.py
fileformats/medimage/raw/pet/__init__.py
fileformats/medimage/raw/pet/base.py
fileformats_medimage-0.11.0.dist-info/METADATA
fileformats_medimage-0.11.0.dist-info/WHEEL
fileformats_medimage-0.11.0.dist-info/licenses/LICENSE
fileformats_medimage-0.11.0.dist-info/RECORD
