Metadata-Version: 2.4
Name: fileformats-medimage
Version: 0.11.0
Summary: Classes for representing various medical imaging file formats in Python classes for use in type hinting in data workflows
Project-URL: repository, https://github.com/ArcanaFramework/fileformats-medimage
Author-email: "Thomas G. Close" <tom.g.close@gmail.com>
Maintainer-email: "Thomas G. Close" <tom.g.close@gmail.com>
License: Creative Commons Attribution 4.0 International Public License
License-File: LICENSE
Keywords: data,file formats
Classifier: Development Status :: 3 - Alpha
Classifier: Environment :: Console
Classifier: Intended Audience :: Science/Research
Classifier: License :: OSI Approved :: Apache Software License
Classifier: Operating System :: MacOS :: MacOS X
Classifier: Operating System :: Microsoft :: Windows
Classifier: Operating System :: POSIX :: Linux
Classifier: Programming Language :: Python :: 3.11
Classifier: Programming Language :: Python :: 3.12
Classifier: Programming Language :: Python :: 3.13
Classifier: Topic :: Scientific/Engineering
Requires-Python: >=3.11
Requires-Dist: fileformats>=0.15
Provides-Extra: dev
Requires-Dist: black; extra == 'dev'
Requires-Dist: codespell; extra == 'dev'
Requires-Dist: flake8; extra == 'dev'
Requires-Dist: flake8-pyproject; extra == 'dev'
Requires-Dist: pre-commit; extra == 'dev'
Requires-Dist: typing-extensions>=4.6; extra == 'dev'
Provides-Extra: test
Requires-Dist: fileformats-medimage-extras; extra == 'test'
Requires-Dist: medimages4tests>=0.3; extra == 'test'
Requires-Dist: mypy>=1.5.1; extra == 'test'
Requires-Dist: pydra-tasks-dcm2niix; extra == 'test'
Requires-Dist: pydra-tasks-mrtrix3>=3.0.4a13; extra == 'test'
Requires-Dist: pytest-cov>=2.12.1; extra == 'test'
Requires-Dist: pytest-env>=0.6.2; extra == 'test'
Requires-Dist: pytest>=6.2.5; extra == 'test'
